netora/__init__.py
netora/__main__.py
netora/connection.py
netora/getinfo.py
netora/netora.py
netora/validation.py
netora/resources/currencies.py
netora_project-0.1.7.dist-info/METADATA
netora_project-0.1.7.dist-info/WHEEL
netora_project-0.1.7.dist-info/entry_points.txt
netora_project-0.1.7.dist-info/top_level.txt
netora_project-0.1.7.dist-info/RECORD
