Metadata-Version: 2.4
Name: netora-project
Version: 0.1.7
Summary: Quickly uncover details and geolocation for any IP address
Author-email: nativevoid <0x4E56@proton.me>
Maintainer-email: nativevoid <0x4E56@proton.me>
Project-URL: Homepage, https://yourhomepage.com
Project-URL: Repository, https://github.com/nativevoid/netora
Project-URL: Bug Tracker, https://github.com/nativevoid/netora/issues
Keywords: geolocation,IP,OSINT
Classifier: Development Status :: 5 - Production/Stable
Classifier: Intended Audience :: Developers
Classifier: Intended Audience :: Information Technology
Classifier: Natural Language :: English
Classifier: Operating System :: OS Independent
Classifier: Programming Language :: Python :: 3
Classifier: Topic :: Security
Requires-Python: >=3.6
Requires-Dist: requests>=2.22.0
Requires-Dist: colorama>=0.4.1
